{
"type": "FeatureCollection",
"name": "sept-2019-VALLENZUOLO-briefcase",
"crs": { "type": "name", "properties": { "name": "urn:ogc:def:crs:OGC:1.3:CRS84" } },
"features": [
{ "type": "Feature", "properties": { "meta-instanceID": "uuid:962cf997-04ff-4199-ba88-4fe5a7b40bcc", "ID": "Lr7", "point": "Ruins", "feelings": "Melancholy", "sense": "Sight ", "class": "Attraction", "picture": "1562260181247.jpg", "location-Latitude": 43.149383654799998, "location-Longitude": 13.370911767699999, "location-Altitude": 419.0, "location-Accuracy": 7.0 }, "geometry": { "type": "Point", "coordinates": [ 13.370911767699999, 43.149383654799998 ] } },
{ "type": "Feature", "properties": { "meta-instanceID": "uuid:9c672921-d238-49e5-a5a4-e614e169baf8", "ID": "Vitto e alloggio", "point": "Chairoplane with pedals", "feelings": "Enthusiasm", "sense": "Sight \/ Hearing", "class": "Attraction", "picture": "1562265552682.jpg", "location-Latitude": 43.163430477, "location-Longitude": 13.356669822100001, "location-Altitude": 460.79104614260001, "location-Accuracy": 4.9 }, "geometry": { "type": "Point", "coordinates": [ 13.356669822100001, 43.163430477 ] } },
{ "type": "Feature", "properties": { "meta-instanceID": "uuid:d0efd233-c0c0-4945-80be-da85d18826f8", "ID": "Vitto e alloggio", "point": "Laundry in nowhere", "feelings": "Terminalia", "sense": "Sight ", "class": "Attraction", "picture": "1562260912738.jpg", "location-Latitude": 43.154977022200001, "location-Longitude": 13.3681520812, "location-Altitude": 354.30315700080001, "location-Accuracy": 4.7 }, "geometry": { "type": "Point", "coordinates": [ 13.3681520812, 43.154977022200001 ] } },
{ "type": "Feature", "properties": { "meta-instanceID": "uuid:d19354e2-fffa-4aac-912f-3b46bf101d6d", "ID": "ME31", "point": "Home that comes out from the wheat", "feelings": "Surprise", "sense": "Sight ", "class": "Attraction", "picture": "1562258187319.jpg", "location-Latitude": 43.146970765100001, "location-Longitude": 13.3700714136, "location-Altitude": 436.25598144529999, "location-Accuracy": 4.7 }, "geometry": { "type": "Point", "coordinates": [ 13.3700714136, 43.146970765100001 ] } },
{ "type": "Feature", "properties": { "meta-instanceID": "uuid:d20bd91f-8089-4f6c-9884-d4c049127dc6", "ID": "MG4", "point": "Farmer's tools hanged on a gate", "feelings": "Nostalgia", "sense": "Sight ", "class": "Attraction", "picture": "null.jpg", "location-Latitude": 43.15276573, "location-Longitude": 13.37105535, "location-Altitude": 421.34112548830001, "location-Accuracy": 4.288 }, "geometry": { "type": "Point", "coordinates": [ 13.37105535, 43.15276573 ] } },
{ "type": "Feature", "properties": { "meta-instanceID": "uuid:305e5f5d-94b9-44d6-828a-d10ea1bf3113", "ID": "DB26", "point": "Wash house", "feelings": "Freshness \/ Familiarity", "sense": "Sight \/ Hearing", "class": "Attraction", "picture": "1562260145549.jpg", "location-Latitude": 43.16315629, "location-Longitude": 13.36107476, "location-Altitude": 392.21398925779999, "location-Accuracy": 4.288 }, "geometry": { "type": "Point", "coordinates": [ 13.36107476, 43.16315629 ] } },
{ "type": "Feature", "properties": { "meta-instanceID": null, "ID": "ME27", "point": "Ruins", "feelings": "Emotional", "sense": "Sight ", "class": "Attraction", "picture": "null.jpg", "location-Latitude": 43.156578, "location-Longitude": 13.367337, "location-Altitude": null, "location-Accuracy": null }, "geometry": { "type": "Point", "coordinates": [ 13.367337, 43.156578 ] } },
{ "type": "Feature", "properties": { "meta-instanceID": null, "ID": "MO31", "point": "Wash house", "feelings": "Quiet", "sense": "Hearing \/ Sight \/ Smell \/ Taste \/ Touch", "class": "Attraction", "picture": "null.jpg", "location-Latitude": 43.163119, "location-Longitude": 13.361073, "location-Altitude": null, "location-Accuracy": null }, "geometry": { "type": "Point", "coordinates": [ 13.361073, 43.163119 ] } },
]
}
